{
  "configVersion": 1,
  "timestamp": 1705971461113,
  "index": "/index.html",
  "assetGroups": [
    {
      "name": "app",
      "installMode": "prefetch",
      "updateMode": "prefetch",
      "cacheQueryOptions": {
        "ignoreVary": true
      },
      "urls": [
        "/chunk-47ND4DYX.js",
        "/chunk-CXN6K2XD.js",
        "/chunk-JBG2UA6E.js",
        "/chunk-OJ2KVZWE.js",
        "/chunk-ZXHESBXK.js",
        "/favicon.ico",
        "/index.html",
        "/main-ZD5RBWKI.js",
        "/manifest.webmanifest",
        "/polyfills-CG2UM2YX.js",
        "/styles-4DOBTHUV.css"
      ],
      "patterns": []
    },
    {
      "name": "assets",
      "installMode": "lazy",
      "updateMode": "prefetch",
      "cacheQueryOptions": {
        "ignoreVary": true
      },
      "urls": [
        "/assets/icons/android-chrome-192x192.png",
        "/assets/icons/android-chrome-512x512.png",
        "/assets/icons/apple-touch-icon.png",
        "/assets/icons/favicon-16x16.png",
        "/assets/icons/favicon-32x32.png"
      ],
      "patterns": []
    }
  ],
  "dataGroups": [],
  "hashTable": {
    "/assets/icons/android-chrome-192x192.png": "efc5832c72125018c99ee0513f0fa691a94befc6",
    "/assets/icons/android-chrome-512x512.png": "774180cce1f51fdbc68414896b85505627b1f812",
    "/assets/icons/apple-touch-icon.png": "b3f527e46181c430f6fd6f7fea8ccbe3c417d604",
    "/assets/icons/favicon-16x16.png": "1f98d03c4e43df6ace155d6aee14b3a3aded23a8",
    "/assets/icons/favicon-32x32.png": "08bfeb096acfb43dd330af0fd5715d6095343ec2",
    "/chunk-47ND4DYX.js": "ff69541a841e992411e81b9c4b972fb416c911fe",
    "/chunk-CXN6K2XD.js": "8e160fcbfaf266da813bfa52bb2e3af9822bcdd3",
    "/chunk-JBG2UA6E.js": "c95521d776f20062d3e3db856da3480afcf39d2a",
    "/chunk-OJ2KVZWE.js": "1414387b78c49ff6347112bdeae00114600333ef",
    "/chunk-ZXHESBXK.js": "ef90685b1eaa791000767203216bc10241e8e11a",
    "/favicon.ico": "0612a0d81b1313c6da6056e10fd3fd401bd771dc",
    "/index.html": "80a2439225121f772bbf1c9b4f0821e05facecde",
    "/main-ZD5RBWKI.js": "36d1ee65ab903df659c0ae9bd55caca97599bda8",
    "/manifest.webmanifest": "9de2038d8797196314fd830ce9264e9de6fc7d19",
    "/polyfills-CG2UM2YX.js": "8758dc9fb93959b8a6c6ee04793c65df80b82558",
    "/styles-4DOBTHUV.css": "f903e72faca528ba3527868045b8ca5ac09513db"
  },
  "navigationUrls": [
    {
      "positive": true,
      "regex": "^\\/.*$"
    },
    {
      "positive": false,
      "regex": "^\\/(?:.+\\/)?[^/]*\\.[^/]*$"
    },
    {
      "positive": false,
      "regex": "^\\/(?:.+\\/)?[^/]*__[^/]*$"
    },
    {
      "positive": false,
      "regex": "^\\/(?:.+\\/)?[^/]*__[^/]*\\/.*$"
    }
  ],
  "navigationRequestStrategy": "performance"
}